{"n_dim": 3, "n_trials": 130, "objective": "salomon_on_cube", "white": "ax_default", "black": "optuna_cmaes", "traceback": ["passing", "passing"], "best_val": [0.8159312511887595, 0.6904374414596844], "best_x": [[0.5037417486383673, 0.5190080975151783, 0.5167905357950664], [0.5093771568671871, 0.5169995243223288, 0.485076931995532]], "feval_count": [130, 130], "n_trials_instructed": [130, 130], "passing": [true, true], "completed": true, "points": 0.0, "winner": "optuna_cmaes_cube", "loser": "ax_default_cube"}