{"n_dim": 3, "n_trials": 210, "objective": "markowitz_analytic_on_cube", "white": "bayesopt_ei", "black": "pymoo_nelder", "traceback": ["passing", "passing"], "best_val": [0.14735322166980988, 0.14524350832371308], "best_x": [[0.3832379253890428, 0.23158020975974936, 0.38438953367986517], [0.36638946046360693, 0.2504617634876206, 0.38314901494134207]], "feval_count": [210, 210], "n_trials_instructed": [210, 210], "passing": [true, true], "completed": true, "points": 0.0, "winner": "pymoo_nelder_cube", "loser": "bayesopt_ei_cube"}