{"n_dim": 3, "n_trials": 210, "objective": "markowitz_return_on_cube", "white": "bobyqa_default", "black": "hyperopt_rand", "traceback": ["passing", "passing"], "best_val": [9758.066982877888, 9758.397126654514], "best_x": [[0.11827859436455869, 0.43649489099743755, 0.439588593169405], [0.23781516167891925, 0.8858371415487596, 0.8820701180159194]], "feval_count": [210, 210], "n_trials_instructed": [210, 210], "passing": [true, true], "completed": true, "points": 0.5, "winner": "draw", "loser": "draw"}