{"n_dim": 5, "n_trials": 210, "objective": "markowitz_realized_on_cube", "white": "bobyqa_default", "black": "dlib", "traceback": ["passing", "passing"], "best_val": [-0.04905931196071229, -0.03940570134422303], "best_x": [[2.634927807798633e-05, 0.07129629585373262, 0.2308805030961108, 0.3637600344199227, 0.33403681705455407], [0.0, 1.0, 0.0, 0.0, 0.0]], "feval_count": [99, 99], "n_trials_instructed": [210, 99], "passing": [true, true], "completed": true, "points": 1.0, "winner": "bobyqa_default", "loser": "dlib"}