{"n_dim": 5, "n_trials": 210, "objective": "markowitz_return_on_cube", "white": "bobyqa_default", "black": "hyperopt_rand", "traceback": ["passing", "passing"], "best_val": [8711.346472301728, 8732.470994059702], "best_x": [[0.36529949991672483, 0.0, 0.3484094576664262, 0.31680066848338867, 0.0], [0.6001687229514419, 0.0005904461770255803, 0.6420480697120436, 0.5287264026600459, 0.0001650582070436581]], "feval_count": [210, 210], "n_trials_instructed": [210, 210], "passing": [true, true], "completed": true, "points": 1.0, "winner": "bobyqa_default", "loser": "hyperopt_rand"}