{"n_dim": 89, "n_trials": 210, "objective": "markowitz_analytic_on_cube", "white": "bobyqa_default", "black": "dlib_default", "traceback": ["passing", "Traceback (most recent call last):\n  File \"/opt/hostedtoolcache/Python/3.8.16/x64/lib/python3.8/site-packages/humpday/comparison/eloratings.py\", line 76, in optimizer_game\n    black_best_val, black_best_x, black_feval_count = black(objective, n_trials=n_black_trials,\n  File \"/opt/hostedtoolcache/Python/3.8.16/x64/lib/python3.8/site-packages/humpday/optimizers/dlibcube.py\", line 27, in dlib_default_cube\n    best_x, best_val = find_min_global(_objective, lb, ub, n_trials)\nRuntimeError: \n\nError detected at line 63.\nError detected in file /tmp/pip-install-8culxgpn/dlib_85af258fda344304a3a9607aba05c3b2/tools/python/src/global_optimization.cpp.\nError detected in function double call_func(pybind11::object, const dlib::matrix<double, 0, 1>&).\n\nFailing expression was 0 < num && num <= 35.\nFunctions being optimized must take between 1 and 35 scalar arguments.\n\n"], "best_val": [0.020444050307299344, null], "best_x": [[0.0, 0.0, 0.0, 0.0, 0.0, 0.0, 0.0, 0.0, 0.0, 0.0, 0.29934201767026297, 0.0, 0.0, 0.0, 0.0, 0.0, 0.0, 0.0, 0.0, 0.1368866420185088, 0.0, 0.0, 0.0, 0.0, 0.0, 0.0, 0.0, 0.19115540065082373, 0.0, 0.0, 0.0, 0.0, 0.0, 0.0, 0.0, 0.009519064103465466, 0.0, 0.0, 0.0025201708300039774, 0.18340079259648276, 0.0, 0.0, 0.0, 0.0, 0.0, 0.0, 0.0, 0.0, 0.0, 0.0, 0.0, 0.0, 0.0, 0.0, 0.0, 0.0, 0.0, 0.0, 0.0, 0.0, 0.0, 0.0, 0.0, 0.0, 0.0, 0.00456152554016348, 0.0, 0.0, 0.0, 0.0, 0.0, 0.02723088819989622, 0.0, 0.0, 0.0, 0.0, 0.14849734395815636, 0.0, 0.0, 0.0, 0.0, 0.0, 0.0, 0.0, 0.0, 0.0, 0.0, 0.0, 0.0], null], "feval_count": [210, null], "n_trials_instructed": [210, 210], "passing": [true, false], "completed": false, "winner": "incomplete", "points": null}