{"n_dim": 5, "n_trials": 80, "objective": "markowitz_skew_on_cube", "white": "dlib_default", "black": "optuna_random_clone", "traceback": ["passing", "passing"], "best_val": [-0.058855000110555084, 0.020449723911398997], "best_x": [[0.0, 1.0, 0.0, 0.0, 0.0], [0.2837768500837716, 0.015606120326099315, 0.45666364026260986, 0.028478429985466458, 0.2920081253872101]], "feval_count": [80, 80], "n_trials_instructed": [80, 80], "passing": [true, true], "completed": true, "points": 1.0, "winner": "dlib_default", "loser": "optuna_random_clone"}