{"n_dim": 3, "n_trials": 80, "objective": "markowitz_analytic_on_cube", "white": "dlib_default", "black": "scipy_lbfgsb", "traceback": ["passing", "passing"], "best_val": [0.20910527132135542, 1.2330971356411218], "best_x": [[0.532111830433852, 0.005197468846117541, 0.46260548681634944], [6.594762486342313e-06, 5.69887328164556e-07, 4.326632613112269e-06]], "feval_count": [80, 113], "n_trials_instructed": [80, 23], "passing": [true, true], "completed": false, "winner": "incomplete", "points": null}