{"n_dim": 3, "n_trials": 130, "objective": "rotated_hyper_ellipsoid_on_cube", "white": "dlib", "black": "pymoo_pattern", "traceback": ["passing", "passing"], "best_val": [4.92536952437516e-20, 5.1965091173318916e-05], "best_x": [[0.49392144246666814, 0.4939214424616189, 0.5023355911276826], [0.49382191351297033, 0.4939122472443449, 0.2577181959666736]], "feval_count": [130, 133], "n_trials_instructed": [130, 130], "passing": [true, true], "completed": true, "points": 1.0, "winner": "dlib", "loser": "pymoo_pattern"}