{"n_dim": 3, "n_trials": 130, "objective": "markowitz_analytic_on_cube", "white": "dlib_default", "black": "scipy_lbfgsb", "traceback": ["passing", "passing"], "best_val": [0.16206994899619975, 1.1782479395694412], "best_x": [[0.12823780396901485, 0.4558343996392041, 0.41592794900639585], [1.8297430167825289e-07, 4.0461192415976054e-07, 4.7555879911259724e-07]], "feval_count": [130, 105], "n_trials_instructed": [130, 130], "passing": [true, true], "completed": true, "points": 1.0, "winner": "dlib_default", "loser": "scipy_lbfgsb"}