{"n_dim": 5, "n_trials": 210, "objective": "markowitz_analytic_on_cube", "white": "dlib", "black": "scipy_slsqp", "traceback": ["passing", "passing"], "best_val": [0.14568100034564568, 1.1068707863208365], "best_x": [[0.21097921651697485, 0.16670625033547182, 0.06542032865949704, 0.422019436011092, 0.13486872836445077], [0.0, 0.0, 0.0, 0.0, 0.0]], "feval_count": [210, 7], "n_trials_instructed": [210, 210], "passing": [true, true], "completed": true, "points": 1.0, "winner": "dlib", "loser": "scipy_slsqp"}