{"n_dim": 5, "n_trials": 80, "objective": "markowitz_analytic_on_cube", "white": "dlib", "black": "shgo_powell_sobol", "traceback": ["passing", "passing"], "best_val": [0.14630318441771306, 1.1053266139040587], "best_x": [[0.3116039309006147, 0.1929795872074167, 0.4263902152898178, 0.0006433325639491665, 0.06841695353898443], [0.0, 2.220446049250313e-16, 0.0, 0.0, 0.0]], "feval_count": [80, 28], "n_trials_instructed": [80, 28], "passing": [true, true], "completed": true, "points": 1.0, "winner": "dlib", "loser": "shgo_powell_sobol"}