{"n_dim": 3, "n_trials": 130, "objective": "markowitz_skew_on_cube", "white": "hebo_batch", "black": "platypus_cmaes", "traceback": ["passing", "passing"], "best_val": [-0.031181301144560095, 0.006748641973494188], "best_x": [[0.00014886134430072738, 7.522920215653219e-05, 0.9998160150502897], [0.03371417280901157, 0.530570943340278, 0.5043453020765359]], "feval_count": [130, 100], "n_trials_instructed": [130, 93], "passing": [true, true], "completed": true, "points": 1.0, "winner": "hebo_batch", "loser": "platypus_cmaes"}