{"n_dim": 3, "n_trials": 130, "objective": "markowitz_skew_on_cube", "white": "hyperopt_rand", "black": "ultraopt_etpe", "traceback": ["passing", "passing"], "best_val": [-0.055925333125726936, -0.030127459315295233], "best_x": [[0.3394143750715236, 0.4110232596921375, 0.2446143914134551], [0.0, 0.6415263382734586, 0.3534895114631413]], "feval_count": [130, 130], "n_trials_instructed": [130, 130], "passing": [true, true], "completed": true, "points": 1.0, "winner": "hyperopt_rand", "loser": "ultraopt_etpe"}