{"n_dim": 3, "n_trials": 210, "objective": "markowitz_realized_on_cube", "white": "hyperopt_atpe", "black": "hyperopt_tpe", "traceback": ["passing", "passing"], "best_val": [-0.02804074077630246, -0.028058947274591788], "best_x": [[0.4192088320886568, 0.5518425684878338, 0.02814964115792607], [0.4152535533517129, 0.47140395560873416, 0.11238934862031236]], "feval_count": [210, 210], "n_trials_instructed": [210, 210], "passing": [true, true], "completed": true, "points": 0.5, "winner": "draw", "loser": "draw"}