{"n_dim": 3, "n_trials": 130, "objective": "landscapes_combo2_on_cube", "white": "hyperopt_rand", "black": "hyperopt_atpe", "traceback": ["passing", "passing"], "best_val": [0.864500371152417, 0.5986387034580349], "best_x": [[0.5141726047151363, 0.5272776460856646, 0.9344146877703531], [0.5276581591186443, 0.5232325203975638, 0.01269556900079788]], "feval_count": [130, 130], "n_trials_instructed": [130, 130], "passing": [true, true], "completed": true, "points": 0.0, "winner": "hyperopt_atpe_cube", "loser": "hyperopt_rand_cube"}