{"n_dim": 8, "n_trials": 80, "objective": "markowitz_realized_on_cube", "white": "hyperopt_atpe", "black": "scipy_lbfgsb", "traceback": ["passing", "passing"], "best_val": [0.7171947872819155, 1.0002910819531778], "best_x": [[0.8296161718129766, 0.0017508927865951818, 0.03645327551454226, 0.3247233862235793, 0.24541428250429617, 0.07249778020068104, 0.0602646725214404, 0.22586815294814028], [0.0, 0.0, 0.0, 0.0, 0.0, 0.0, 0.0, 0.0]], "feval_count": [80, 10], "n_trials_instructed": [80, 80], "passing": [true, true], "completed": true, "points": 1.0, "winner": "hyperopt_atpe", "loser": "scipy_lbfgsb"}