{"n_dim": 3, "n_trials": 210, "objective": "markowitz_skew_on_cube", "white": "hyperopt_tpe", "black": "shgo_powell_sobol", "traceback": ["passing", "passing"], "best_val": [-0.03373442591089046, -0.037587637031502065], "best_x": [[0.6602148959558745, 0.08103129532042065, 0.2601768623509577], [0.6034954145069638, 6.714972531577533e-19, 0.39650458530886407]], "feval_count": [210, 323], "n_trials_instructed": [210, 65], "passing": [true, true], "completed": false, "winner": "incomplete", "points": null}