{"n_dim": 3, "n_trials": 80, "objective": "markowitz_return_on_cube", "white": "hyperopt_rand", "black": "bobyqa_default", "traceback": ["passing", "passing"], "best_val": [8380.474196403808, 8359.313963878703], "best_x": [[0.8372147074975214, 0.42688030188981274, 0.6490963435005398], [0.4922605267221779, 0.2470878952921838, 0.42291647066091803]], "feval_count": [80, 80], "n_trials_instructed": [80, 80], "passing": [true, true], "completed": true, "points": 0.0, "winner": "bobyqa_default_cube", "loser": "hyperopt_rand_cube"}