{"n_dim": 3, "n_trials": 130, "objective": "michaelewicz_on_cube", "white": "hyperopt_tpe", "black": "platypus_epsmoea", "traceback": ["passing", "passing"], "best_val": [1.2870399325442596, 1.3205006534370696], "best_x": [[0.1383794590849261, 0.8065270035275296, 0.8984077706018131], [0.9071864634638878, 0.2680118887282177, 0.7453797106077517]], "feval_count": [130, 130], "n_trials_instructed": [130, 130], "passing": [true, true], "completed": true, "points": 1.0, "winner": "hyperopt_tpe", "loser": "platypus_epsmoea"}