{"n_dim": 3, "n_trials": 130, "objective": "markowitz_return_on_cube", "white": "hyperopt_rand", "black": "hyperopt_atpe", "traceback": ["passing", "passing"], "best_val": [39101.08349970604, 39017.03466287546], "best_x": [[0.09997109656085855, 0.5225633891919246, 0.002889918436997296], [0.17283015548568784, 0.9032600030475458, 0.0016609817637592858]], "feval_count": [130, 130], "n_trials_instructed": [130, 130], "passing": [true, true], "completed": true, "points": 0.0, "winner": "hyperopt_atpe_cube", "loser": "hyperopt_rand_cube"}