{"n_dim": 5, "n_trials": 130, "objective": "markowitz_analytic_on_cube", "white": "hyperopt_atpe", "black": "shgo_nelder_sobol", "traceback": ["passing", "passing"], "best_val": [0.07571370131014353, 1.1014526875831645], "best_x": [[0.3250794777310826, 0.2807790719286176, 0.19802707458818175, 0.1285230744907131, 0.07067654680049752], [4.440892098500626e-16, 0.0, 1.6653345369377348e-16, 1.1102230246251565e-16, 0.0]], "feval_count": [130, 76], "n_trials_instructed": [130, 110], "passing": [true, true], "completed": true, "points": 1.0, "winner": "hyperopt_atpe", "loser": "shgo_nelder_sobol"}