{"n_dim": 2, "n_trials": 80, "objective": "markowitz_realized_on_cube", "white": "optuna_random_clone_2", "black": "optuna_cmaes", "traceback": ["passing", "passing"], "best_val": [-0.015139878694470966, -0.018710569425132297], "best_x": [[0.1805166479172211, 0.8185131636516456], [0.4563985870659668, 0.5436354638478892]], "feval_count": [80, 80], "n_trials_instructed": [80, 80], "passing": [true, true], "completed": true, "points": 0.0, "winner": "optuna_cmaes_cube", "loser": "optuna_random_cube_clone_2"}