{"n_dim": 3, "n_trials": 340, "objective": "deap_combo3_on_cube", "white": "platypus_smpso", "black": "ultraopt_etpe", "traceback": ["passing", "passing"], "best_val": [79877.46017507171, 95092.2274226729], "best_x": [[0.5549094140982103, 0.5607076020073488, 0.7181669953625914], [0.5283599341009515, 0.5350225703501325, 0.4464993063072762]], "feval_count": [300, 300], "n_trials_instructed": [237, 300], "passing": [true, true], "completed": true, "points": 1.0, "winner": "platypus_smpso", "loser": "ultraopt_etpe"}