{"n_dim": 8, "n_trials": 80, "objective": "bohachevsky_on_cube", "white": "platypus_gde3", "black": "pymoo_unsga3", "traceback": ["passing", "passing"], "best_val": [81.32152594062445, null], "best_x": [[0.7681609860920647, 0.6536573205674227, 0.3173442888651913, 0.24073967690429132, 0.4766645381752924, 0.32046356759041505, 0.694807888134547, 0.47060136982376], null], "feval_count": [100, null], "n_trials_instructed": [18, null], "passing": [true, null], "completed": false, "winner": "incomplete", "points": null}