{"n_dim": 3, "n_trials": 130, "objective": "markowitz_analytic_on_cube", "white": "platypus_ibea", "black": "pymoo_nsga3", "traceback": ["passing", "passing"], "best_val": [0.3396904863872132, 0.3733456732195251], "best_x": [[0.177589014750427, 0.1755796046836562, 0.555459010263201], [0.3754154193465571, 0.059186742573930085, 0.5651838916721637]], "feval_count": [100, 100], "n_trials_instructed": [91, 100], "passing": [true, true], "completed": true, "points": 1.0, "winner": "platypus_ibea", "loser": "pymoo_nsga3"}