{"n_dim": 3, "n_trials": 130, "objective": "markowitz_realized_on_cube", "white": "platypus_moead", "black": "skopt_gp_default", "traceback": ["passing", "Black took 131 function evals when instructed to use 131"], "best_val": [-0.02856211368904082, -0.02853819698600897], "best_x": [[0.2803563682201712, 0.7191458036643603, 0.00046582828611752003], [0.0, 0.23896380685226257, 0.7608500758165284]], "feval_count": [131, 131], "n_trials_instructed": [130, 131], "passing": [true, true], "completed": true, "points": 0.5, "winner": "draw", "loser": "draw"}