{"n_dim": 3, "n_trials": 210, "objective": "markowitz_analytic_on_cube", "white": "platypus_nsgaii", "black": "hebo_sequential", "traceback": ["passing", "passing"], "best_val": [0.9224448965556811, 0.8401878472376342], "best_x": [[0.2931459228604031, 0.6400977235124876, 0.03256579285052874], [0.17895591854274773, 0.821014263672746, 3.2800630622720206e-07]], "feval_count": [196, 196], "n_trials_instructed": [147, 196], "passing": [true, true], "completed": true, "points": 0.0, "winner": "hebo_cube_sequential", "loser": "platypus_nsgaii_cube"}