{"n_dim": 3, "n_trials": 210, "objective": "styblinski_tang_on_cube", "white": "platypus_smpso", "black": "hyperopt_atpe", "traceback": ["passing", "passing"], "best_val": [2.190910991654139, 2.2060884661023055], "best_x": [[0.22619847130743798, 0.2600512565022213, 0.2743640825332183], [0.23555238660870964, 0.2773774946112543, 0.2924920104059546]], "feval_count": [200, 200], "n_trials_instructed": [147, 200], "passing": [true, true], "completed": true, "points": 1.0, "winner": "platypus_smpso", "loser": "hyperopt_atpe"}