{"n_dim": 3, "n_trials": 130, "objective": "landscapes_combo3_on_cube", "white": "platypus_ibea", "black": "optuna_cmaes", "traceback": ["passing", "passing"], "best_val": [1.2303803871102468, 1.2219009272069445], "best_x": [[0.6108787206898942, 0.7277618835817634, 0.7318629674274705], [0.8364324258863658, 0.683271578248665, 0.7709668407832291]], "feval_count": [100, 100], "n_trials_instructed": [91, 100], "passing": [true, true], "completed": true, "points": 0.0, "winner": "optuna_cmaes_cube", "loser": "platypus_ibea_cube"}