{"n_dim": 8, "n_trials": 80, "objective": "markowitz_skew_on_cube", "white": "platypus_cmaes", "black": "nlopt_direct", "traceback": ["passing", "passing"], "best_val": [0.7820194134303148, null], "best_x": [[0.47099380920154715, 0.09501540129781733, 0.096627245285139, 0.2714680994211522, 0.4027359691053619, 0.012982181143983418, 0.20358266397722818, 0.3056742714845954], null], "feval_count": [100, null], "n_trials_instructed": [18, null], "passing": [true, null], "completed": false, "winner": "incomplete", "points": null}