{"n_dim": 8, "n_trials": 80, "objective": "styblinski_tang_on_cube", "white": "platypus_smpso", "black": "shgo_nelder_sobol", "traceback": ["passing", "passing"], "best_val": [-194.32065828375877, null], "best_x": [[0.15890588883577172, 0.2416465466052775, 0.08372629991752889, 0.21826973704307484, 0.24326930550376225, 0.72426013791795, 0.6928040765888345, 0.4162234203526951], null], "feval_count": [100, null], "n_trials_instructed": [18, null], "passing": [true, null], "completed": false, "winner": "incomplete", "points": null}