{"n_dim": 3, "n_trials": 130, "objective": "drop_wave_on_cube", "white": "platypus_cmaes", "black": "platypus_gde3", "traceback": ["passing", "passing"], "best_val": [-0.7833591260259772, -0.7779521542699658], "best_x": [[0.44388873961050873, 0.3800521806594308, 0.39175294418050194], [0.6073737447417334, 0.4647648690750332, 0.2865187024999145]], "feval_count": [100, 100], "n_trials_instructed": [91, 100], "passing": [true, true], "completed": true, "points": 1.0, "winner": "platypus_cmaes", "loser": "platypus_gde3"}