{"n_dim": 3, "n_trials": 210, "objective": "rosenbrock_on_cube", "white": "platypus_gde3", "black": "platypus_evolutionary", "traceback": ["passing", "passing"], "best_val": [11187981.825850423, 1044995.6434857016], "best_x": [[0.487792840061242, 0.5311239121124987, 0.2689264116543969], [0.5230072418725742, 0.4993555534705284, 0.8869572417704463]], "feval_count": [200, 198], "n_trials_instructed": [147, 170], "passing": [true, true], "completed": true, "points": 0.0, "winner": "platypus_evolutionary_cube", "loser": "platypus_gde3_cube"}