{"n_dim": 3, "n_trials": 130, "objective": "qing_on_cube", "white": "pymoo_nsga2", "black": "optuna_random_clone_2", "traceback": ["passing", "passing"], "best_val": [198080752301.65765, 6817946440.014019], "best_x": [[0.6719217319559155, 0.47052638185303564, 0.6928813324971437], [0.6288735980770679, 0.6981452208630613, 0.5902379267854266]], "feval_count": [100, 100], "n_trials_instructed": [91, 100], "passing": [true, true], "completed": true, "points": 0.0, "winner": "optuna_random_cube_clone_2", "loser": "pymoo_nsga2_cube"}