{"n_dim": 3, "n_trials": 210, "objective": "landscapes_combo2_on_cube", "white": "pymoo_nsga3", "black": "optuna_random_clone", "traceback": ["passing", "passing"], "best_val": [0.01413564196897902, 3.004903207604411], "best_x": [[0.5240410582302678, 0.5261776631160598, 0.5242759960483737], [0.5782946938838771, 0.5480172276572578, 0.5041167513660291]], "feval_count": [210, 210], "n_trials_instructed": [210, 210], "passing": [true, true], "completed": true, "points": 1.0, "winner": "pymoo_nsga3", "loser": "optuna_random_clone"}