{"n_dim": 8, "n_trials": 130, "objective": "markowitz_analytic_on_cube", "white": "pymoo_pattern", "black": "scipy_lbfgsb", "traceback": ["passing", "passing"], "best_val": [0.10140188935940284, 1.0759944043577956], "best_x": [[0.125, 0.0, 0.15489060292126744, 0.0, 0.0, 0.4316899296434009, 0.0625, 0.2532413358349255], [0.0, 1.982547687488837e-10, 1.9825476874888166e-10, 0.0, 0.0, 0.0, 1.9825476874888288e-10, 1.982547687488879e-10]], "feval_count": [133, 289], "n_trials_instructed": [130, 40], "passing": [true, true], "completed": false, "winner": "incomplete", "points": null}