{"n_dim": 8, "n_trials": 210, "objective": "markowitz_return_on_cube", "white": "pymoo_unsga3", "black": "scipy_slsqp", "traceback": ["passing", "passing"], "best_val": [3116.277964725738, 6434.3986846896305], "best_x": [[0.7093794370603681, 0.608750262496925, 0.3186037093333832, 0.5734968842644496, 0.8846685738659306, 0.462007633407978, 0.665101768548899, 0.9544441867626416], [0.0, 0.0, 0.0, 0.0, 0.0, 0.0, 0.0, 0.0]], "feval_count": [210, 10], "n_trials_instructed": [210, 210], "passing": [true, true], "completed": true, "points": 1.0, "winner": "pymoo_unsga3", "loser": "scipy_slsqp"}