{"n_dim": 3, "n_trials": 80, "objective": "markowitz_realized_on_cube", "white": "pymoo_pattern", "black": "bayesopt_poi", "traceback": ["passing", "Black took 83 function evals when instructed to use 83"], "best_val": [-0.022849063617776545, -0.025440110367303894], "best_x": [[1.0, 0.0, 0.0], [0.23239053082124128, 0.0628168632519569, 0.7052628232245085]], "feval_count": [83, 83], "n_trials_instructed": [80, 83], "passing": [true, true], "completed": true, "points": 0.0, "winner": "bayesopt_poi_cube", "loser": "pymoo_pattern_cube"}