{"n_dim": 3, "n_trials": 130, "objective": "salomon_on_cube", "white": "pysot_random", "black": "pysot_ei", "traceback": ["passing", "passing"], "best_val": [1.8018661427109202, 0.3266059518418556], "best_x": [[0.5803905530773904, 0.6274177817817954, 0.7306161235859656], [0.6659722153328608, 0.6279587264227238, 0.6512088915110302]], "feval_count": [130, 130], "n_trials_instructed": [130, 130], "passing": [true, true], "completed": true, "points": 0.0, "winner": "pysot_ei_cube", "loser": "pysot_random_cube"}