{"n_dim": 34, "n_trials": 80, "objective": "markowitz_analytic_on_cube", "white": "scipy_lbfgsb", "black": "hyperopt_tpe", "traceback": ["passing", "passing"], "best_val": [1.0145010393722373, null], "best_x": [[2.2057943712399557e-10, 0.0, 0.0, 0.0, 0.0, 0.0, 0.0, 2.2057943712400382e-10, 0.0, 0.0, 0.0, 0.0, 0.0, 0.0, 0.0, 0.0, 0.0, 2.2057943712421932e-10, 0.0, 0.0, 0.0, 2.2057943712414666e-10, 0.0, 2.2057943712432926e-10, 0.0, 0.0, 0.0, 0.0, 0.0, 0.0, 0.0, 2.2057943712399684e-10, 2.2057943712412999e-10, 2.2057943712426456e-10], null], "feval_count": [1086, null], "n_trials_instructed": [18, null], "passing": [true, null], "completed": false, "winner": "incomplete", "points": null}