{"n_dim": 3, "n_trials": 210, "objective": "deap_combo3_on_cube", "white": "scipy_slqsp", "black": "pymoo_nsga3", "traceback": ["passing", "passing"], "best_val": [5.910728125970034, 559.1965176284293], "best_x": [[0.5332536478695591, 0.5325636657341607, 0.532600820062048], [0.5376103209018133, 0.5443641684279428, 0.5625943739334872]], "feval_count": [135, 135], "n_trials_instructed": [210, 135], "passing": [true, true], "completed": true, "points": 1.0, "winner": "scipy_slqsp", "loser": "pymoo_nsga3"}