{"n_dim": 3, "n_trials": 130, "objective": "landscapes_combo1_on_cube", "white": "scipy_dogleg", "black": "pysot_ei", "traceback": ["passing", "passing"], "best_val": [0.831816933258062, 10779144352.627207], "best_x": [[0.6499276555653449, 0.6496859052175973, 0.6494719944559657], [0.7175872757740205, 0.5684043562551757, 0.6098735631420419]], "feval_count": [87, 87], "n_trials_instructed": [130, 87], "passing": [true, true], "completed": true, "points": 1.0, "winner": "scipy_dogleg", "loser": "pysot_ei"}