{"n_dim": 8, "n_trials": 80, "objective": "markowitz_skew_on_cube", "white": "scipy_slsqp", "black": "bayesopt_ucb", "traceback": ["passing", "passing"], "best_val": [0.990870013593893, 0.33236043403299176], "best_x": [[0.0, 0.0, 0.0, 0.0, 0.0, 0.0, 0.0, 0.0], [0.11428413942656095, 1.0, 0.0, 0.10991860501008077, 0.0, 0.0, 0.22674460621582543, 0.0]], "feval_count": [10, 10], "n_trials_instructed": [80, 10], "passing": [true, true], "completed": true, "points": 0.0, "winner": "bayesopt_ucb_cube", "loser": "scipy_slsqp_cube"}