{"n_dim": 3, "n_trials": 130, "objective": "markowitz_realized_on_cube", "white": "scipy_slsqp", "black": "bobyqa_default", "traceback": ["passing", "passing"], "best_val": [-0.028938197381761954, -0.028737830181232084], "best_x": [[0.30821372106751616, 0.1375805946169778, 0.5542051676774934], [0.5558739256838099, 0.02432337647930849, 0.4198026923868193]], "feval_count": [81, 66], "n_trials_instructed": [130, 81], "passing": [true, true], "completed": true, "points": 1.0, "winner": "scipy_slsqp", "loser": "bobyqa_default"}