{"n_dim": 8, "n_trials": 210, "objective": "rosenbrock_modified_on_cube", "white": "scipy_powell", "black": "shgo_powell_sobol", "traceback": ["passing", "passing"], "best_val": [-4144.084599255204, -4137.0], "best_x": [[6.610696135189609e-05, 6.610696135189609e-05, 6.610696135189609e-05, 6.610696135189609e-05, 6.610696135189609e-05, 6.610696135189609e-05, 6.610696135189609e-05, 0.9999338930386481], [0.0, 0.0, 0.0, 0.0, 0.0, 0.0, 0.0, 0.0]], "feval_count": [162, 99], "n_trials_instructed": [147, 162], "passing": [true, true], "completed": true, "points": 0.5, "winner": "draw", "loser": "draw"}