{"n_dim": 8, "n_trials": 210, "objective": "markowitz_realized_on_cube", "white": "scipy_slsqp", "black": "shgo_nelder_sobol", "traceback": ["passing", "passing"], "best_val": [-0.07805865206465336, 1.0003273223510276], "best_x": [[0.043959250577217134, 0.0, 2.5261282404802213e-17, 0.38646711759165064, 0.020341903928499046, 0.054595710290704334, 0.49463543193606524, 9.072026472550684e-19], [0.0, 0.0, 0.0, 0.0, 0.0, 0.0, 0.0, 0.0]], "feval_count": [135, 147], "n_trials_instructed": [210, 135], "passing": [true, true], "completed": true, "points": 1.0, "winner": "scipy_slsqp", "loser": "shgo_nelder_sobol"}