{"n_dim": 8, "n_trials": 80, "objective": "markowitz_realized_on_cube", "white": "scipy_powell", "black": "dlib", "traceback": ["passing", "Black took 81 function evals when instructed to use 81"], "best_val": [-0.07460966506130232, -0.07792322777410024], "best_x": [[0.9999338930386481, 6.610696135189609e-05, 6.610696135189609e-05, 0.0, 0.0, 0.0, 0.0, 0.0], [0.0, 0.0632522195859722, 0.9363721244387047, 0.0004038005016917021, 7.126263997526543e-14, 0.0, 0.0, 0.0]], "feval_count": [81, 81], "n_trials_instructed": [80, 81], "passing": [true, true], "completed": true, "points": 0.0, "winner": "dlib_cube", "loser": "scipy_powell_cube"}