{"n_dim": 21, "n_trials": 80, "objective": "markowitz_return_on_cube", "white": "scipy_slsqp", "black": "scipy_lbfgsb", "traceback": ["passing", "passing"], "best_val": [1307.3679189360375, 1273.9347424061352], "best_x": [[0.0, 0.0, 0.0, 0.0, 0.0, 0.0, 0.0, 0.0, 0.0, 0.0, 0.0, 0.0, 0.0, 0.0, 0.0, 0.0, 0.0, 0.0, 0.0, 0.0, 0.0], [0.0, 0.0, 0.0, 4.1054582591444786e-10, 0.0, 4.1054582591432663e-10, 0.0, 0.0, 4.1054582591437916e-10, 0.0, 0.0, 0.0, 0.0, 4.10545825914553e-10, 0.0, 0.0, 0.0, 4.1054582591461273e-10, 4.1054582591416683e-10, 0.0, 0.0]], "feval_count": [23, 661], "n_trials_instructed": [80, 5], "passing": [true, true], "completed": false, "winner": "incomplete", "points": null}