{"n_dim": 13, "n_trials": 210, "objective": "markowitz_return_on_cube", "white": "scipy_lbfgsb", "black": "scipy_powell", "traceback": ["passing", "passing"], "best_val": [3310.6961773020744, null], "best_x": [[0.0, 0.0, 6.8200210488265416e-06, 2.2792805870389783e-06, 2.712881445016125e-06, 0.0, 1.4239526689762166e-06, 6.3849676571761606e-06, 1.8459073465357644e-06, 0.0, 3.398527407280854e-06, 1.564217598347778e-06, 2.0537245047723258e-06], null], "feval_count": [435, null], "n_trials_instructed": [49, null], "passing": [true, null], "completed": false, "winner": "incomplete", "points": null}