{"n_dim": 13, "n_trials": 340, "objective": "markowitz_analytic_on_cube", "white": "scipy_lbfgsb", "black": "hyperopt_rand", "traceback": ["passing", "passing"], "best_val": [1.0421802800674116, null], "best_x": [[1.273761523686858e-09, 0.0, 1.2513399446296915e-09, 0.0, 1.2513399446296915e-09, 0.0, 1.2513399446296915e-09, 1.2513399446296915e-09, 1.2513399446296915e-09, 0.0, 0.0, 0.0, 0.0], null], "feval_count": [715, null], "n_trials_instructed": [80, null], "passing": [true, null], "completed": false, "winner": "incomplete", "points": null}