{"n_dim": 8, "n_trials": 130, "objective": "shaffer_on_cube", "white": "shgo_powell_sobol", "black": "nevergrad_oneplus", "traceback": ["passing", "passing"], "best_val": [2.891915850959138, null], "best_x": [[0.4997145802168778, 0.49971453310158387, 0.49971458021896104, 0.49971453309926855, 0.49971458021990434, 0.49971453310121283, 0.4997145802151667, 0.4997145331047805], null], "feval_count": [157, null], "n_trials_instructed": [30, null], "passing": [true, null], "completed": false, "winner": "incomplete", "points": null}