{"n_dim": 8, "n_trials": 130, "objective": "markowitz_analytic_on_cube", "white": "shgo_powell_sobol", "black": "dlib", "traceback": ["passing", "passing"], "best_val": [1.1819744714608797, 0.4316901429907643], "best_x": [[0.0, 0.0, 0.0, 0.0, 0.0, 0.0, 0.0, 0.0], [0.000146465958052105, 0.9999856575691155, 2.4022107643658093e-08, 0.0006562774911008358, 3.5580999723496613e-06, 0.08731622331496627, 0.0, 4.620407580276059e-05]], "feval_count": [83, 83], "n_trials_instructed": [91, 83], "passing": [true, true], "completed": true, "points": 0.0, "winner": "dlib_cube", "loser": "shgo_powell_sobol_cube"}