{"n_dim": 3, "n_trials": 210, "objective": "markowitz_analytic_on_cube", "white": "shgo_powell_sobol", "black": "bobyqa_noise", "traceback": ["passing", "Black took 106 function evals when instructed to use 226"], "best_val": [0.12233844789609105, 0.12279340727282309], "best_x": [[0.32812260684828637, 0.31728201157180935, 0.3545953770281394], [0.34079315426185336, 0.30259711738663714, 0.3566097280015071]], "feval_count": [226, 106], "n_trials_instructed": [49, 226], "passing": [true, true], "completed": true, "points": 1.0, "winner": "shgo_powell_sobol", "loser": "bobyqa_noise"}