{"n_dim": 8, "n_trials": 210, "objective": "markowitz_realized_on_cube", "white": "shgo_slsqp_sobol", "black": "bobyqa_noise", "traceback": ["passing", "passing"], "best_val": [1.0003548954674009, -0.0697540682639854], "best_x": [[0.0, 0.0, 0.0, 0.0, 0.0, 0.0, 0.0, 0.0], [0.028550444303533727, 0.0005412959419766416, 0.1138436120520091, 0.0, 0.7424890619940907, 0.0012249784799060553, 0.0, 0.11335058549948723]], "feval_count": [119, 119], "n_trials_instructed": [210, 119], "passing": [true, true], "completed": true, "points": 0.0, "winner": "bobyqa_noise_cube", "loser": "shgo_slsqp_sobol_cube"}