{"n_dim": 8, "n_trials": 210, "objective": "markowitz_realized_on_cube", "white": "shgo_powell_sobol", "black": "hyperopt_atpe", "traceback": ["passing", "passing"], "best_val": [-0.07963705556485286, null], "best_x": [[0.09103492276451204, 0.12044912897965, 0.21016992379651445, 0.09356777289679084, 0.09405288888270129, 0.10966053057393789, 0.07979911161373472, 0.2012657166354792], null], "feval_count": [458, null], "n_trials_instructed": [49, null], "passing": [true, null], "completed": false, "winner": "incomplete", "points": null}