{"n_dim": 8, "n_trials": 80, "objective": "markowitz_return_on_cube", "white": "shgo_slsqp_sobol", "black": "hyperopt_atpe", "traceback": ["passing", "passing"], "best_val": [2825.98090663935, null], "best_x": [[0.12302174230904711, 0.11799410278994647, 0.10007690856254592, 0.12586127951524903, 0.1294875680949318, 0.1465474273371893, 0.12293132667526954, 0.13407963381620694], null], "feval_count": [900, null], "n_trials_instructed": [18, null], "passing": [true, null], "completed": false, "winner": "incomplete", "points": null}