{"n_dim": 8, "n_trials": 80, "objective": "markowitz_realized_on_cube", "white": "shgo_nelder_sobol", "black": "hyperopt_tpe", "traceback": ["passing", "passing"], "best_val": [-0.07902305634728517, null], "best_x": [[1.0471851159979735e-18, 0.060060950536038674, 0.08768227005926746, 0.35047318346493284, 0.0677816667884238, 3.590723691565258e-19, 0.0076840811957761025, 0.42631784381475657], null], "feval_count": [300, null], "n_trials_instructed": [18, null], "passing": [true, null], "completed": false, "winner": "incomplete", "points": null}