{"n_dim": 3, "n_trials": 210, "objective": "markowitz_return_on_cube", "white": "shgo_powell_sobol", "black": "scipy_lbfgsb", "traceback": ["passing", "Black took 5 function evals when instructed to use 221"], "best_val": [8661.424810347431, 10057.310257162997], "best_x": [[0.5732766333787331, 0.8449582272635048, 0.6749051060425312], [0.0, 0.0, 0.0]], "feval_count": [221, 5], "n_trials_instructed": [49, 221], "passing": [true, true], "completed": true, "points": 1.0, "winner": "shgo_powell_sobol", "loser": "scipy_lbfgsb"}