{"n_dim": 3, "n_trials": 210, "objective": "markowitz_skew_on_cube", "white": "shgo_slsqp_sobol", "black": "dlib", "traceback": ["passing", "Black took 229 function evals when instructed to use 229"], "best_val": [-0.04108200912133278, -0.033326777937820504], "best_x": [[1.9326692980763676e-18, 0.11851107681842818, 0.8814889192114961], [0.0001592842648965758, 0.5546539168195307, 0.44518679891544904]], "feval_count": [229, 229], "n_trials_instructed": [49, 229], "passing": [true, true], "completed": true, "points": 1.0, "winner": "shgo_slsqp_sobol", "loser": "dlib"}