{"n_dim": 8, "n_trials": 80, "objective": "markowitz_realized_on_cube", "white": "skopt_gp_default", "black": "scipy_lbfgsb", "traceback": ["passing", "passing"], "best_val": [-0.07483453760872331, 1.0003218473640936], "best_x": [[0.0, 0.8365548456852526, 0.0, 0.0, 0.1638322135863496, 0.0, 0.0, 0.0], [0.0, 2.1905596575686352e-10, 0.0, 0.0, 0.0, 0.0, 2.1905596575686352e-10, 4.528214412849338e-09]], "feval_count": [80, 469], "n_trials_instructed": [80, 23], "passing": [true, true], "completed": false, "winner": "incomplete", "points": null}