{"n_dim": 3, "n_trials": 80, "objective": "markowitz_realized_on_cube", "white": "skopt_gp_default", "black": "bobyqa_default", "traceback": ["passing", "passing"], "best_val": [-0.02767424563976966, -0.028955674055440063], "best_x": [[0.5842796646891223, 0.2742837589581494, 0.14272761965830158], [0.4192434250996562, 0.02408720292210312, 0.5566693651273851]], "feval_count": [80, 63], "n_trials_instructed": [80, 80], "passing": [true, true], "completed": true, "points": 0.0, "winner": "bobyqa_default_cube", "loser": "skopt_gp_default_cube"}