{"n_dim": 5, "n_trials": 80, "objective": "markowitz_return_on_cube", "white": "skopt_gp_default", "black": "shgo_slsqp_sobol", "traceback": ["passing", "passing"], "best_val": [4728.947637869207, 4711.022911169688], "best_x": [[0.629580592323435, 1.0, 1.0, 0.6165440325418171, 0.9071212974458955], [0.1682941503808912, 0.23350619533490236, 0.22702804894616443, 0.13809253451817322, 0.22716382828061663]], "feval_count": [80, 274], "n_trials_instructed": [80, 23], "passing": [true, true], "completed": false, "winner": "incomplete", "points": null}