{"n_dim": 3, "n_trials": 130, "objective": "markowitz_analytic_on_cube", "white": "skopt_gp_default", "black": "ultraopt_forest", "traceback": ["passing", "passing"], "best_val": [0.8824793943064082, 0.8933716146099416], "best_x": [[0.4024807811865768, 0.5974058433128258, 0.0], [0.47953419160063315, 0.5125765166081031, 0.007816666441962106]], "feval_count": [130, 130], "n_trials_instructed": [130, 130], "passing": [true, true], "completed": true, "points": 1.0, "winner": "skopt_gp_default", "loser": "ultraopt_forest"}