{"n_dim": 8, "n_trials": 210, "objective": "markowitz_return_on_cube", "white": "ultraopt_random", "black": "scipy_slsqp", "traceback": ["passing", "passing"], "best_val": [4459.520138418893, 10823.84595422022], "best_x": [[0.5187906217433661, 0.7030189588951778, 0.363629602379294, 0.9717820827209607, 0.9624472949421112, 0.25178229582536416, 0.49724850589238545, 0.30087830981676966], [0.0, 0.0, 0.0, 0.0, 0.0, 0.0, 0.0, 0.0]], "feval_count": [210, 10], "n_trials_instructed": [210, 210], "passing": [true, true], "completed": true, "points": 1.0, "winner": "ultraopt_random", "loser": "scipy_slsqp"}