{"n_dim": 5, "n_trials": 210, "objective": "markowitz_skew_on_cube", "white": "ultraopt_etpe", "black": "hyperopt_tpe", "traceback": ["passing", "passing"], "best_val": [-0.08866730036551537, -0.07963083034313509], "best_x": [[0.41245597987489824, 0.0, 0.38799177882144714, 0.0, 0.20395489823988575], [0.5512191776815767, 0.10641156965785467, 0.049418071875010294, 0.2590765535114416, 0.028159701833952777]], "feval_count": [210, 210], "n_trials_instructed": [210, 210], "passing": [true, true], "completed": true, "points": 1.0, "winner": "ultraopt_etpe", "loser": "hyperopt_tpe"}