{"n_dim": 5, "n_trials": 130, "objective": "markowitz_realized_on_cube", "white": "ultraopt_etpe", "black": "shgo_powell_sobol", "traceback": ["passing", "passing"], "best_val": [-0.047653467858483185, -0.04951534453999921], "best_x": [[0.0, 0.0, 0.0, 1.0, 0.0], [0.11433244588604981, 0.16516330080394445, 0.30339174024844817, 0.2664879135840782, 0.1506245981763338]], "feval_count": [130, 200], "n_trials_instructed": [130, 39], "passing": [true, true], "completed": false, "winner": "incomplete", "points": null}