{"n_dim": 3, "n_trials": 210, "objective": "markowitz_realized_on_cube", "white": "ultraopt_forest", "black": "shgo_powell_sobol", "traceback": ["passing", "passing"], "best_val": [-0.027075288682179684, -0.028860969005575075], "best_x": [[0.1317833210824234, 0.35159502513348573, 0.5163144891362053], [0.21028117891444453, 0.11973407732596923, 0.6699847402109887]], "feval_count": [210, 819], "n_trials_instructed": [210, 65], "passing": [true, true], "completed": false, "winner": "incomplete", "points": null}